pypuns/__init__.py
pypuns/pypuns.py
pypuns/puns/__init__.py
pypuns/puns/en.py
pypuns/puns/it.py
pypuns/puns/lang_template.py
pypuns/puns/languages.py
pypuns-0.4.2.0.dist-info/LICENSE
pypuns-0.4.2.0.dist-info/METADATA
pypuns-0.4.2.0.dist-info/WHEEL
pypuns-0.4.2.0.dist-info/top_level.txt
pypuns-0.4.2.0.dist-info/RECORD
