Metadata-Version: 2.1
Name: pypuns
Version: 0.4.2.0
Summary: Simple random puns picker
Home-page: https://github.com/PyPuns/PyPuns
Author: Bunz
Author-email: 66bunz@gmail.com
License: UNKNOWN
Project-URL: Bug Reports, https://github.com/PyPuns/PyPuns/issues
Project-URL: Funding, https://www.buymeacoffee.com/66bunz
Project-URL: Say Thanks!, https://saythanks.io/to/66Bunz
Project-URL: Source, https://github.com/PyPuns/PyPuns
Keywords: python,puns,pypuns,chatbots,chat,jokes,random jokes,random joke,joke,pun,random pun,random puns
Platform: UNKNOWN
Classifier: Development Status :: 4 - Beta
Classifier: Intended Audience :: Developers
Classifier: Programming Language :: Python :: 3
Classifier: License :: OSI Approved :: GNU Affero General Public License v3
Classifier: Natural Language :: English
Classifier: Natural Language :: Italian
Classifier: Topic :: Software Development :: Build Tools
Classifier: Operating System :: OS Independent
License-File: LICENSE
